README.rst
setup.py
fastpm/__init__.py
fastpm/background.py
fastpm/core.py
fastpm/glass.py
fastpm/hold.py
fastpm/main.py
fastpm/multi.py
fastpm/naivepppm.py
fastpm/nbkit.py
fastpm/ncdm.py
fastpm/operators.py
fastpm/state.py
fastpm/utils.py
fastpm/version.py
fastpm.egg-info/PKG-INFO
fastpm.egg-info/SOURCES.txt
fastpm.egg-info/dependency_links.txt
fastpm.egg-info/requires.txt
fastpm.egg-info/top_level.txt
fastpm/force/__init__.py
fastpm/force/gravity.py
fastpm/force/kernels.py
fastpm/force/lpt.py
fastpm/force/pmgravity.py
fastpm/tests/__init__.py
fastpm/tests/test_core.py
fastpm/tests/test_glass.py
fastpm/tests/test_hold.py
fastpm/tests/test_kernel.py
fastpm/tests/test_multi.py
fastpm/tests/test_nbkit.py
fastpm/tests/test_ncdm.py
fastpm/tests/test_state.py