Metadata-Version: 1.0
Name: fastpm
Version: 0.0.10
Summary: FastPM in Python
Home-page: UNKNOWN
Author: Yu Feng
Author-email: UNKNOWN
License: UNKNOWN
Platform: UNKNOWN
